ratarmountcore/BlockParallelReaders.py
ratarmountcore/ProgressBar.py
ratarmountcore/SQLiteBlobFile.py
ratarmountcore/SQLiteIndex.py
ratarmountcore/SQLiteIndexedTarFsspec.py
ratarmountcore/StenciledFile.py
ratarmountcore/__init__.py
ratarmountcore/compressions.py
ratarmountcore/formats.py
ratarmountcore/utils.py
ratarmountcore/version.py
ratarmountcore/_external/__init__.py
ratarmountcore/_external/pyfatfs/BootSectorHeader.py
ratarmountcore/_external/pyfatfs/DosDateTime.py
ratarmountcore/_external/pyfatfs/EightDotThree.py
ratarmountcore/_external/pyfatfs/FATDirectoryEntry.py
ratarmountcore/_external/pyfatfs/FSInfo.py
ratarmountcore/_external/pyfatfs/FatIO.py
ratarmountcore/_external/pyfatfs/LICENSE
ratarmountcore/_external/pyfatfs/PyFat.py
ratarmountcore/_external/pyfatfs/__init__.py
ratarmountcore/_external/pyfatfs/_exceptions.py
ratarmountcore/mountsource/MountSource.py
ratarmountcore/mountsource/SQLiteIndexMountSource.py
ratarmountcore/mountsource/__init__.py
ratarmountcore/mountsource/archives.py
ratarmountcore/mountsource/factory.py
ratarmountcore/mountsource/compositing/automount.py
ratarmountcore/mountsource/compositing/removeprefix.py
ratarmountcore/mountsource/compositing/singlefile.py
ratarmountcore/mountsource/compositing/subvolumes.py
ratarmountcore/mountsource/compositing/union.py
ratarmountcore/mountsource/compositing/versioning.py
ratarmountcore/mountsource/formats/asar.py
ratarmountcore/mountsource/formats/ext4.py
ratarmountcore/mountsource/formats/fat.py
ratarmountcore/mountsource/formats/folder.py
ratarmountcore/mountsource/formats/fsspec.py
ratarmountcore/mountsource/formats/git.py
ratarmountcore/mountsource/formats/libarchive.py
ratarmountcore/mountsource/formats/py7zr.py
ratarmountcore/mountsource/formats/rar.py
ratarmountcore/mountsource/formats/sqlar.py
ratarmountcore/mountsource/formats/squashfs.py
ratarmountcore/mountsource/formats/tar.py
ratarmountcore/mountsource/formats/zip.py
ratarmountcore-0.10.2.dist-info/licenses/LICENSE
ratarmountcore-0.10.2.dist-info/licenses/ratarmountcore/_external/pyfatfs/LICENSE
ratarmountcore-0.10.2.dist-info/METADATA
ratarmountcore-0.10.2.dist-info/WHEEL
ratarmountcore-0.10.2.dist-info/entry_points.txt
ratarmountcore-0.10.2.dist-info/top_level.txt
ratarmountcore-0.10.2.dist-info/RECORD
